pandas_dev_flaker/__init__.py
pandas_dev_flaker/__main__.py
pandas_dev_flaker/_ast_helpers.py
pandas_dev_flaker/_data_tokens.py
pandas_dev_flaker/_data_tree.py
pandas_dev_flaker/_plugins_tokens/__init__.py
pandas_dev_flaker/_plugins_tokens/strings_to_concatenate.py
pandas_dev_flaker/_plugins_tokens/wrongplaced_whitespace.py
pandas_dev_flaker/_plugins_tree/__init__.py
pandas_dev_flaker/_plugins_tree/api_types.py
pandas_dev_flaker/_plugins_tree/bare_pytest_raises.py
pandas_dev_flaker/_plugins_tree/builtin_filter.py
pandas_dev_flaker/_plugins_tree/class.py
pandas_dev_flaker/_plugins_tree/collections_abc.py
pandas_dev_flaker/_plugins_tree/common.py
pandas_dev_flaker/_plugins_tree/conftest.py
pandas_dev_flaker/_plugins_tree/contextless_pytest_raises.py
pandas_dev_flaker/_plugins_tree/disallow_argument_types.py
pandas_dev_flaker/_plugins_tree/exec_usage.py
pandas_dev_flaker/_plugins_tree/generator_join_strings.py
pandas_dev_flaker/_plugins_tree/namespace_usage.py
pandas_dev_flaker/_plugins_tree/np_bool_object.py
pandas_dev_flaker/_plugins_tree/numpy_random.py
pandas_dev_flaker/_plugins_tree/numpy_testing.py
pandas_dev_flaker/_plugins_tree/os_remove.py
pandas_dev_flaker/_plugins_tree/pandas__testing.py
pandas_dev_flaker/_plugins_tree/pandas_testing.py
pandas_dev_flaker/_plugins_tree/private_imports.py
pandas_dev_flaker/_plugins_tree/pytest_warns.py
pandas_dev_flaker/_plugins_tree/pytest_xfail.py
pandas_dev_flaker/_plugins_tree/repr.py
pandas_dev_flaker/_plugins_tree/single_letter_variables.py
pandas_dev_flaker/_plugins_tree/unitest_mock.py
pandas_dev_flaker-0.5.0.dist-info/LICENSE
pandas_dev_flaker-0.5.0.dist-info/METADATA
pandas_dev_flaker-0.5.0.dist-info/WHEEL
pandas_dev_flaker-0.5.0.dist-info/entry_points.txt
pandas_dev_flaker-0.5.0.dist-info/top_level.txt
pandas_dev_flaker-0.5.0.dist-info/RECORD
