Metadata-Version: 2.1
Name: pandas-dev-flaker
Version: 0.5.0
Summary: Linter for contributing to pandas
Home-page: https://github.com/pandas-dev/pandas-dev-flaker
Author: PyData Development Team
License: MIT
Platform: UNKNOWN
Classifier: License :: OSI Approved :: MIT License
Classifier: Programming Language :: Python :: 3
Classifier: Programming Language :: Python :: 3 :: Only
Classifier: Programming Language :: Python :: 3.6
Classifier: Programming Language :: Python :: 3.7
Classifier: Programming Language :: Python :: 3.8
Classifier: Programming Language :: Python :: 3.9
Classifier: Programming Language :: Python :: Implementation :: CPython
Classifier: Programming Language :: Python :: Implementation :: PyPy
Requires-Python: >=3.6.1
Requires-Dist: flake8 (>=3.8)
Requires-Dist: importlib-metadata (>=0.9) ; python_version < "3.8"
